Verilog_TASK_1/Prac_2 Source code/adders.v
// HALF ADDER
module half_adder (s,cout,a,b);
input a,b;
output s,cout;
assign s=a^b;
assign cout =a&b;

endmodule

// FULL ADDER
module full_adder (s,cout,a,b,cin);
input a,b,cin;
output s,cout;
assign s=a^b^cin;
assign cout =a&b|(cin&(a^b));

endmodule

Verilog_TASK_1/Prac_2 Source code/adders_tb.v
// TEST BENCH
`timescale 1ps/1ps
`include "adders.v"

module stimulus;
// reg A,B;
reg A,B,CIN;
wire S,COUT;

// half_adder h(S,COUT,A,B);
 full_adder f1(S,COUT,A,B,CIN);

initial begin
    // $monitor($time, "A=%b, B=%b, S=%b, COUT=%b", A,B,S,COUT);
    $monitor($time, "A=%b, B=%b,CIN=%b, S=%b, COUT=%b", A,B,CIN,S,COUT);

//     // TEST CASES
//     A=0; B=0;
// #5  A=0; B=1;    
// #5  A=1; B=0;    
// #5  A=1; B=1;    

A=0; B=0; CIN=0;
#5 A=0; B=0; CIN=1;
#5 A=0; B=1; CIN=0;
#5 A=0; B=1; CIN=1;
#5 A=1; B=0; CIN=0;
#5 A=1; B=0; CIN=1;
#5 A=1; B=1; CIN=0;
#5 A=1; B=1; CIN=1;

#5 $finish;

end 
initial begin
    $dumpfile("adders.vcd");
    $dumpvars(0,stimulus);
end
endmodule

Verilog_TASK_1/Prac_2 Source code/adders.vcd
$date
	Wed Aug 19 10:26:17 2026
$end
$version
	Icarus Verilog
$end
$timescale
	1ps
$end
$scope module stimulus $end
$var wire 1 ! S $end
$var wire 1 " COUT $end
$var reg 1 # A $end
$var reg 1 $ B $end
$var reg 1 % CIN $end
$scope module f1 $end
$var wire 1 # a $end
$var wire 1 $ b $end
$var wire 1 % cin $end
$var wire 1 " cout $end
$var wire 1 ! s $end
$upscope $end
$upscope $end
$enddefinitions $end
$comment Show the parameter values. $end
$dumpall
$end
#0
$dumpvars
0%
0$
0#
0"
0!
$end
#5
1!
1%
#10
0%
1$
#15
1"
0!
1%
#20
0"
1!
0%
0$
1#
#25
1"
0!
1%
#30
0%
1$
#35
1!
1%
